qiskit_nature/VERSION.txt
qiskit_nature/__init__.py
qiskit_nature/constants.py
qiskit_nature/exceptions.py
qiskit_nature/logging.py
qiskit_nature/optionals.py
qiskit_nature/py.typed
qiskit_nature/settings.py
qiskit_nature/units.py
qiskit_nature/version.py
qiskit_nature/second_q/__init__.py
qiskit_nature/second_q/algorithms/__init__.py
qiskit_nature/second_q/algorithms/excited_states_solvers/__init__.py
qiskit_nature/second_q/algorithms/excited_states_solvers/excited_states_eigensolver.py
qiskit_nature/second_q/algorithms/excited_states_solvers/excited_states_solver.py
qiskit_nature/second_q/algorithms/excited_states_solvers/qeom.py
qiskit_nature/second_q/algorithms/excited_states_solvers/qeom_electronic_ops_builder.py
qiskit_nature/second_q/algorithms/excited_states_solvers/qeom_vibrational_ops_builder.py
qiskit_nature/second_q/algorithms/ground_state_solvers/__init__.py
qiskit_nature/second_q/algorithms/ground_state_solvers/ground_state_eigensolver.py
qiskit_nature/second_q/algorithms/ground_state_solvers/ground_state_solver.py
qiskit_nature/second_q/algorithms/initial_points/__init__.py
qiskit_nature/second_q/algorithms/initial_points/hf_initial_point.py
qiskit_nature/second_q/algorithms/initial_points/initial_point.py
qiskit_nature/second_q/algorithms/initial_points/mp2_initial_point.py
qiskit_nature/second_q/algorithms/initial_points/vscf_initial_point.py
qiskit_nature/second_q/circuit/__init__.py
qiskit_nature/second_q/circuit/library/__init__.py
qiskit_nature/second_q/circuit/library/bogoliubov_transform.py
qiskit_nature/second_q/circuit/library/ansatzes/__init__.py
qiskit_nature/second_q/circuit/library/ansatzes/chc.py
qiskit_nature/second_q/circuit/library/ansatzes/puccd.py
qiskit_nature/second_q/circuit/library/ansatzes/puccsd.py
qiskit_nature/second_q/circuit/library/ansatzes/succd.py
qiskit_nature/second_q/circuit/library/ansatzes/ucc.py
qiskit_nature/second_q/circuit/library/ansatzes/uccsd.py
qiskit_nature/second_q/circuit/library/ansatzes/uvcc.py
qiskit_nature-0.7.2.dist-info/LICENSE.txt
qiskit_nature-0.7.2.dist-info/METADATA
qiskit_nature-0.7.2.dist-info/WHEEL
qiskit_nature-0.7.2.dist-info/top_level.txt
qiskit_nature-0.7.2.dist-info/RECORD
