Metadata-Version: 2.1
Name: qiskit-nature
Version: 0.7.2
Summary: Qiskit Nature: A library of quantum computing chemistry/physics experiments
Home-page: https://github.com/Qiskit/qiskit-nature
Author: Qiskit Nature Development Team
Author-email: qiskit@us.ibm.com
License: Apache-2.0
Project-URL: Bug Tracker, https://github.com/Qiskit/qiskit-nature/issues
Project-URL: Documentation, https://qiskit-community.github.io/qiskit-nature/
Project-URL: Source Code, https://github.com/Qiskit/qiskit-nature
Keywords: qiskit sdk quantum nature chemistry physics
Classifier: Environment :: Console
Classifier: License :: OSI Approved :: Apache Software License
Classifier: Intended Audience :: Developers
Classifier: Intended Audience :: Science/Research
Classifier: Operating System :: Microsoft :: Windows
Classifier: Operating System :: MacOS
Classifier: Operating System :: POSIX :: Linux
Classifier: Programming Language :: Python :: 3 :: Only
Classifier: Programming Language :: Python :: 3.8
Classifier: Programming Language :: Python :: 3.9
Classifier: Programming Language :: Python :: 3.10
Classifier: Programming Language :: Python :: 3.11
Classifier: Programming Language :: Python :: 3.12
Classifier: Topic :: Scientific/Engineering
Requires-Python: >=3.8
License-File: LICENSE.txt
Requires-Dist: qiskit>=0.44
Requires-Dist: qiskit-algorithms>=0.2.1
Requires-Dist: scipy>=1.4
Requires-Dist: numpy>=1.17
Requires-Dist: psutil>=5
Requires-Dist: setuptools>=40.1.0
Requires-Dist: typing_extensions
Requires-Dist: h5py
Requires-Dist: rustworkx>=0.12
Provides-Extra: pyscf
Requires-Dist: pyscf; sys_platform != "win32" and extra == "pyscf"
Provides-Extra: mpl
Requires-Dist: matplotlib>=3.3; extra == "mpl"
Provides-Extra: sparse
Requires-Dist: sparse; extra == "sparse"
Provides-Extra: opt-einsum
Requires-Dist: opt_einsum; extra == "opt-einsum"
